articlib/articFileUtils.py
articlib/consoleUtils.py
articlib/dateTime.py
articlib/dice.py
articlib/jsonHandler.py
articlib/logUtils.py
articlib/py.typed
articlib/sqliteEngine.py
articlib-0.2.9.dist-info/LICENSE
articlib-0.2.9.dist-info/METADATA
articlib-0.2.9.dist-info/WHEEL
articlib-0.2.9.dist-info/RECORD
