Metadata-Version: 2.1
Name: articlib
Version: 0.2.9
Summary: Small set of tools and utilities in python. Destined to be use in my personal projects.
License: MIT
Author: Artic42
Author-email: engineer@artic42.com
Requires-Python: >=3.10,<4.0
Classifier: License :: OSI Approved :: MIT License
Classifier: Programming Language :: Python :: 3
Classifier: Programming Language :: Python :: 3.10
Classifier: Programming Language :: Python :: 3.11
Classifier: Programming Language :: Python :: 3.12
Classifier: Programming Language :: Python :: 3.13
Requires-Dist: colorama (>=0.4.6,<0.5.0)
Requires-Dist: pytest (>=9.0.2,<10.0.0)
